distributions_hlowy/Binomialdistribution_challenge.py
distributions_hlowy/Gaussiandistribution.py
distributions_hlowy/Generaldistribution.py
distributions_hlowy/__init__.py
distributions_hlowy-0.1.dist-info/licenses/LICENSE
distributions_hlowy-0.1.dist-info/METADATA
distributions_hlowy-0.1.dist-info/WHEEL
distributions_hlowy-0.1.dist-info/top_level.txt
distributions_hlowy-0.1.dist-info/RECORD
