Metadata-Version: 2.4
Name: distributions_hlowy
Version: 0.1
Summary: Gaussian distributions
Author: H Lowy
License: MIT
Project-URL: Source, https://github.com/HWLowy/distributions_hlowy
Project-URL: Issues, https://github.com/HWLowy/distributions_hlowy/issues
Classifier: Programming Language :: Python :: 3
Classifier: Operating System :: OS Independent
Requires-Python: >=3.6
License-File: LICENSE
Requires-Dist: matplotlib
Dynamic: license
Dynamic: license-file
Dynamic: summary
